egor/__init__.py
egor/commands.py
egor/config.py
egor/entry.py
egor/help.py
egor/invocation.py
egor/meta.py
egor/task.py
egor/util.py
egor/judge/__init__.py
egor/judge/builder.py
egor/judge/checker.py
egor/judge/verdict.py
egor/judge/langs/__init__.py
egor/judge/langs/cpp_builder.py
egor/judge/langs/java_builder.py
egor/server/__init__.py
egor/server/server.py
egor/templates/__init__.py
egor/templates/template.cpp
egor/templates/template.java
egor-1.0.1.dist-info/LICENSE
egor-1.0.1.dist-info/METADATA
egor-1.0.1.dist-info/WHEEL
egor-1.0.1.dist-info/entry_points.txt
egor-1.0.1.dist-info/top_level.txt
egor-1.0.1.dist-info/RECORD
