Metadata-Version: 2.1
Name: egor
Version: 1.0.1
Summary: A Task automation tool for competitive programmers
Home-page: https://github.com/chermehdi/egor
Author: Cheracher Mehdi
Author-email: mehdi.cheracher@gmail.com
License: MIT
Platform: UNKNOWN
Classifier: Intended Audience :: Developers
Classifier: Programming Language :: Python
Classifier: Programming Language :: Python :: 3
Classifier: Programming Language :: Python :: 3.5
Classifier: Programming Language :: Python :: 3.6
Classifier: Programming Language :: Python :: 3.7
Classifier: License :: OSI Approved :: MIT License
Requires-Dist: knack
Requires-Dist: urllib3
Requires-Dist: pyperclip
Requires-Dist: colorama
Requires-Dist: enum34 ; python_version>="3.6"
